tutorial.py
pixiv_utils/__init__.py
pixiv_utils/image_mix/__init__.py
pixiv_utils/image_mix/bvh_tree.py
pixiv_utils/image_mix/mix_image.py
pixiv_utils/image_mix/utils.py
pixiv_utils/pixiv_crawler/__init__.py
pixiv_utils/pixiv_crawler/config.py
pixiv_utils/pixiv_crawler/utils.py
pixiv_utils/pixiv_crawler/collector/__init__.py
pixiv_utils/pixiv_crawler/collector/collector.py
pixiv_utils/pixiv_crawler/collector/collector_unit.py
pixiv_utils/pixiv_crawler/collector/selectors.py
pixiv_utils/pixiv_crawler/crawlers/__init__.py
pixiv_utils/pixiv_crawler/crawlers/bookmark_crawler.py
pixiv_utils/pixiv_crawler/crawlers/keyword_crawler.py
pixiv_utils/pixiv_crawler/crawlers/ranking_crawler.py
pixiv_utils/pixiv_crawler/crawlers/users_crawler.py
pixiv_utils/pixiv_crawler/downloader/__init__.py
pixiv_utils/pixiv_crawler/downloader/download_image.py
pixiv_utils/pixiv_crawler/downloader/downloader.py
pixiv_utils-1.0.2.dist-info/LICENSE
pixiv_utils-1.0.2.dist-info/METADATA
pixiv_utils-1.0.2.dist-info/WHEEL
pixiv_utils-1.0.2.dist-info/top_level.txt
pixiv_utils-1.0.2.dist-info/RECORD
