Metadata-Version: 2.1
Name: pixiv-utils
Version: 1.0.2
Summary: Pixiv Utils implemented in Python, including Pixiv crawler and mosaic puzzles, support for rankings, personal favorites, artist works, keyword search and other filtering functions, and provide high-performance multi-threaded parallel download.
Home-page: https://github.com/CWHer/PixivCrawler
Author: Wenhao Chen
Author-email: cwher@outlook.com
Classifier: Programming Language :: Python :: 3
Classifier: License :: OSI Approved :: MIT License
Classifier: Operating System :: OS Independent
Requires-Python: >=3.9
License-File: LICENSE
Requires-Dist: beautifulsoup4>=4.12
Requires-Dist: colorama>=0.4
Requires-Dist: numpy>=1.26
Requires-Dist: Pillow>=10.3
Requires-Dist: Requests>=2.32
Requires-Dist: setuptools>=69.5
Requires-Dist: tqdm>=4.64
